diva/__init__.py
diva/analytics_converters.py
diva/converters.py
diva/dashboard.py
diva/exceptions.py
diva/reporter.py
diva/utilities.py
diva/utils.py
diva/widgets.py
diva/static/.DS_Store
diva/static/apple-touch-icon.png
diva/static/browserconfig.xml
diva/static/crossdomain.xml
diva/static/favicon.ico
diva/static/humans.txt
diva/static/main.css
diva/static/normalize.css
diva/static/plugins.js
diva/static/reports.js
diva/static/robots.txt
diva/static/script.js
diva/static/style.css
diva/static/style.css.map
diva/static/style.scss
diva/static/tile-wide.png
diva/static/tile.png
diva/static/utilities.js
diva/static/widgets.js
diva/static/vendor/.DS_Store
diva/static/vendor/FileSaver.min.js
diva/static/vendor/bootstrap-timepicker.min.css
diva/static/vendor/bootstrap-timepicker.min.js
diva/static/vendor/modernizr-2.8.3.min.js
diva/templates/.DS_Store
diva/templates/.index.html.swp
diva/templates/.label_widget.html.swp
diva/templates/checkbox_widget.html
diva/templates/checklist_widget.html
diva/templates/dashboard.html
diva/templates/index.html
diva/templates/input_tag_widget.html
diva/templates/label_widget.html
diva/templates/radio_widget.html
diva/templates/slider_widget.html
diva/templates/utility_button.html
diva/templates/utility_form.html
diva/templates/utility_label.html
diva/templates/widgetform.html
diva-0.1.5.dist-info/DESCRIPTION.rst
diva-0.1.5.dist-info/METADATA
diva-0.1.5.dist-info/RECORD
diva-0.1.5.dist-info/WHEEL
diva-0.1.5.dist-info/metadata.json
diva-0.1.5.dist-info/top_level.txt
